stackModule/__init__.py
stackModule/stack-module.usage.py
stackModule/stackModule.py
stack_module-0.1.4.dist-info/METADATA
stack_module-0.1.4.dist-info/WHEEL
stack_module-0.1.4.dist-info/top_level.txt
stack_module-0.1.4.dist-info/RECORD
