Metadata-Version: 2.1
Name: stack-module
Version: 0.1.4
Summary: An example of a stack in Python 3
Home-page: https://github.com/dudeisbrendan03/stack-example
Author: Brendan T D. Jennings
Author-email: jbrendan70@outlook.com
License: LICENSE
Platform: UNKNOWN
Classifier: Programming Language :: Python :: 3
Classifier: License :: OSI Approved :: GNU General Public License v3 or later (GPLv3+)
Classifier: Operating System :: OS Independent
